dqv/__init__.py
dqv/data_quality_validation_pydeequ.py
dqv/datacheckmate.py
dqv/dqv_pydeequ.py
Data_Checkmate-1.5.dist-info/METADATA
Data_Checkmate-1.5.dist-info/WHEEL
Data_Checkmate-1.5.dist-info/top_level.txt
Data_Checkmate-1.5.dist-info/RECORD
